[
    {
        "id": 900,
        "question": "ما هي وظيفة الكاربوريتر في المركبة؟",
        "a": "مزج الهواء بالوقود بغية احداث خليط يحترق لتشغيل المحرك",
        "b": "تنظيف الوقود الذي يدخل الى خزان الوقود",
        "c": "لتحرير البخار الذي يتكون من حرارة المحرك",
        "d": "مزج البخار في داخل المحرك",
        "answer": "1"
    },
    {
        "id": 901,
        "question": "ما هي وظيفة التشوك (الخانق) في المركبة؟",
        "a": "تكوين خليط غني بالوقود لتسهيل تشغيل المحرك بالجو البارد وخصوصا في الصباح",
        "b": "تكوين خليط غني بالهواء لتسهيل تشغيل المحرك وخصوصا في الصباح",
        "c": "ايصال الكهرباء بصورة سريعة للمحرك",
        "d": "تسخين المحرك",
        "answer": "1"
    },
    {
        "id": 902,
        "question": "الخليط من الوقود والهواء الضروري لتشغيل المحرك يتكون",
        "a": "في الكاربوريتر",
        "b": "في المولد",
        "c": "في الرادياتير",
        "d": "في الكارتير",
        "answer": "1"
    },
    {
        "id": 903,
        "question": "عند الضغط على دعسة الكلاتش",
        "a": "تزيد القوة المنقولة من المحرك الى العجلات",
        "b": "تزيد سرعة المركبة وخصوصا في طريق صاعدة",
        "c": "لا ينقل المحرك القوة لتحريك العجلات",
        "d": "يتصل المحرك مع جهاز الغيارات",
        "answer": "3"
    },
    {
        "id": 904,
        "question": "عندما لا تصل الشرارة الكهربائية للبوجيات",
        "a": "هذا يؤثر فقط عند تشغيل المحرك صباحا",
        "b": "المحرك لا يعمل",
        "c": "هذا يؤثر على المحرك فقط عند السير بسرعة",
        "d": "المحرك يتوقف عن العمل بانتظام",
        "answer": "2"
    },
    {
        "id": 905,
        "question": "عندما يكون ضغط الهواء في الاطارات اكثر من المطلوب",
        "a": "تقل سرعة المركبة",
        "b": "تزيد سرعة المركبة",
        "c": "تكون المركبة اكثر حساسية للاهتزازات",
        "d": "يصعب توجيه المقود يمنة او يسرة",
        "answer": "3"
    },
    {
        "id": 906,
        "question": "ما هو ترتيب العمليات اللازمة لتغيير عجل ؟",
        "a": "فتح البراغي قليلا ، رفع المركبة ثم فتح البراغي تماما",
        "b": "فتح جميع البراغي تماما ثم رفع العجل",
        "c": "فتح برغيين متقابلين اولا ثم رفع المركبة وفتح باقي البراغي",
        "d": "رفع العجل اولا ثم فتح جميع البراغي",
        "answer": "1"
    },
    {
        "id": 907,
        "question": "يجب ان يكون ضغط الهواء في الاطارات",
        "a": "حسب تعليمات المنتج",
        "b": "حسب تعليملت القانون",
        "c": "حسب عرض الاطار",
        "d": "حسب مساحة لمس الاطار",
        "answer": "1"
    },
    {
        "id": 908,
        "question": "عندما يتوقف محرك البنزين بصورة فجائية فما عليك فحصه أولا",
        "a": "اذا كان هناك ماء كافي في الراديتر",
        "b": "اذا كان هناك زيت كاف في المحرك",
        "c": "اذا أضواء المركبة تنير",
        "d": "اذا كان هناك خلل في التيار الكهربائي",
        "answer": "4"
    },
    {
        "id": 909,
        "question": "ما هي وظيفة البطارية",
        "a": "خزن التيار الكهربائي",
        "b": "قياس التيار الكهربائي",
        "c": "توليد التيار الكهربائي",
        "d": "فصل التيار الكهربائي",
        "answer": "1"
    },
    {
        "id": 910,
        "question": "ماذا ترينا ساعة ضغط الزيت أو لمبة ضغط الزيت",
        "a": "ترينا كمية الزيت في حوض الزيت",
        "b": "ترينا كمية الزيت الذي يجب أن نضيفه",
        "c": "ترينا كمية الزيت في المحرك",
        "d": "ترينا مقدار ضغط الزيت في المحرك أثناء عمله",
        "answer": "4"
    },
    {
        "id": 911,
        "question": "اذا كانت كمية الزيت ناقصة في الكارتير ( حوض الزيت)",
        "a": "ممنوع تحريك المركبة يجب احضار ميكانيكي",
        "b": "يجب اضافة الكمية الناقصة في اقرب محطة وقود.",
        "c": "يجب اضافة الكمية الناقصة عند تشحيم المركبة",
        "d": "يجب السير الى اقرب كراج لتصليح الكارتير.",
        "answer": "2"
    },
    {
        "id": 912,
        "question": "انت تسير بمركبة ، وتشعر بان عملية المقود تختلف عما كان بالأمس ،فما عليك عمله",
        "a": "ان نضيف حالا زيت لمحور المقود",
        "b": "ان  توقف المركبة وان نغير العجلات الامامية فيما بينهما",
        "c": "ان نشد برغي المقود داخل المركبة",
        "d": "ان تتوجه حالا للكراج لإصلاح المقود",
        "answer": "4"
    },
    {
        "id": 913,
        "question": "كيف نلاحظ ان حزام المروحة قد انقطع",
        "a": "عندما تسمع صوتا غريبا من المحرك",
        "b": "عند فتح غطاء المحرك",
        "c": "عندما يتوقف المحرك عن العمل",
        "d": "عندما تضيء ساعة الامبير وترتفع درجة حرارة الماء في المحرك",
        "answer": "4"
    },
    {
        "id": 914,
        "question": "اذا كان ضغط الهواء في الإطارات غير صحيح فالإطارات تتلف بسرعة",
        "a": "لا اهمية للأمر",
        "b": "غير صحيح",
        "c": "صحيح",
        "d": "هذا صحيح بالنسبة للعجلات الامامية فقط",
        "answer": "3"
    },
    {
        "id": 915,
        "question": "يرينا مقياس السرعة",
        "a": "سرعة سير المركبة  كم / ساعة",
        "b": "سرعة دوران المحرك",
        "c": "سرعة العجلات المسننة في جهاز الغيارات",
        "d": "سرعة دوران عجلة المحرك",
        "answer": "1"
    },
    {
        "id": 916,
        "question": "يرينا مقياس ضغط الزيت",
        "a": "اذا كان الزيت يصل الى جميع الأجزاء المتحركة في المحرك",
        "b": "صلاحية فيلتر الزيت",
        "c": "كمية الزيت في الكارتيير",
        "d": "نوعية الزيت وموعد تغييره",
        "answer": "1"
    },
    {
        "id": 917,
        "question": "عندما لا يمكن تشغيل المحرك ، وتشعر برائحة الوقود، وهناك شك بأن الكاربوريتر مشبع",
        "a": "عليك التشغيل لتضيف وقود للكاربوريتر",
        "b": "عليك الاستمرار بتشغيل المحرك الى أن يتبخر الوقود",
        "c": "عليك الانتظار قليلا الى أن يتبخر الوقود ، بعد ذلك تشغل المحرك",
        "d": "عليك التشغيل بفترات قصيرة الى أن يشتعل الوقود",
        "answer": "3"
    },
    {
        "id": 918,
        "question": "يرينا مقياس الوقود",
        "a": "عدد الكيلومترات التي قطعتها المركبة",
        "b": "كمية الوقود في خزان الوقود",
        "c": "صلاحية جهاز الوقود",
        "d": "نوعية الوقود وعدد الاوكتان فيه",
        "answer": "2"
    },
    {
        "id": 919,
        "question": "جهاز تغيير الاضواء في المركبة يمكن السائق من",
        "a": "تغيير الضوء العالي الى نور الطريق",
        "b": "تغيير الضوء الواطئ الى نور الالتقاء",
        "c": "جميع الاجابات صحيحة",
        "d": "تغيير الضوء العالي الى الواطئ وبالعكس",
        "answer": "4"
    },
    {
        "id": 920,
        "question": "يجب تغيير الزيت في حوض الزيت / الكارتيير",
        "a": "بعد عدد من الكيلومترات حسب تعليمات المنتج",
        "b": "عندما تكون كمية الزيت داخل المحرك أقل من المطلوب",
        "c": "حسب تعليمات سلطة الترخيص",
        "d": "عندما تشعر بأن كثافة الزيت عالية جداً",
        "answer": "1"
    },
    {
        "id": 921,
        "question": "يضيء مصباح تحذير الاضواء في لوحة المقاييس",
        "a": "عندما نستعمل مصابيح الوقوف",
        "b": "عندما نستعمل نور الالتقاء",
        "c": "عندما نستعمل الضوء العالي",
        "d": "عندما نستعمل الضوء الواطئ",
        "answer": "3"
    },
    {
        "id": 922,
        "question": "في المركبات الحديثة يوجد مصباح لجهاز الفرامل يضيء",
        "a": "في كل حالة عند عدم استعمال فرامل اليد",
        "b": "عندما تسخن بطانة الفرامل",
        "c": "في كل حالة عند استعمال فرامل الرجل",
        "d": "عندما يكون هناك نقص في سائل الفرامل",
        "answer": "4"
    },
    {
        "id": 2095,
        "question": "ما هو جهاز مراقبة التوازن (الثبات) الالكتروني في المركبة (إي-إس. بي) (E.S.P):",
        "a": "جهاز يمنع إمكانية حدوث خلل في جهاز فرامل المركبة.",
        "b": "جهاز يمنع إمكانية حدوث خلل في جهاز مقود المركبة.",
        "c": "جهاز يصحح أخطاء السائق عند الفرملة يمنع التزحلق ويساعد على زيادة توازن المركبة.",
        "d": "جهاز يمنع إقفال عجلات المركبة عند الفرملة الفجائية، وبهذا تتم المحافظة على عمل مقود المركبة.",
        "answer": "3"
    },
    {
        "id": 2096,
        "question": "أي جزء في المركبة يقلل من تأرجح الرأس إلى الخلف أثناء الاصطدام؟",
        "a": "ساندة الرأس في مقاعد المركبة.",
        "b": "المصد (الطمبون) الخلفي.",
        "c": "وسادة الهواء.",
        "d": "حزام الأمان.",
        "answer": "1"
    },
    {
        "id": 2097,
        "question": "أية ملحقات تخفف من خطورة إصابة الركاب عند وقوع حادث طرق؟",
        "a": "أحزمة الأمان وساندات الرأس ووسائد الهواء.",
        "b": "مصابيح الضباب والمقاعد الطبية.",
        "c": "ماسحات الزجاج الخلفية وساندات الرأس.",
        "d": "دعسات الفرامل والكلاتش.",
        "answer": "1"
    },
    {
        "id": 2098,
        "question": "من اجل الانتقال بالغيار من وضع الوقوف (P) إلى وضع السير (R) أو (D)، في مركبة ذات صندوق غيارات أوتوماتكية :",
        "a": "يجب الضغط على مفتاح (زر) التشغيل حيث يحدث التعشيق بشكلٍ أوتوماتيكي.",
        "b": "يجب الضغط على دعسة الكلاتش وتعشيق عصا الغيارات.",
        "c": "يجب الضغط على دعسة الفرامل وعلى زر التشغيل في عصا الغيارات وتعشيق عصا الغيارات حسب وضع السير.",
        "d": "يجب الضغط على دعسة الفرامل حيث يحدث التعشيق بشكلٍ أوتوماتيكي.",
        "answer": "3"
    },
    {
        "id": 2099,
        "question": "لماذا يجب استعمال فرملة الوقوف (الهاندبريك)-عند الوقوف فقط؟",
        "a": "لأن عمرها قصير ولا يجب استنفاذها على الفرملة العادية.",
        "b": "لا يجوز استعمال فرملة الوقوف (الهاندبريك) كفرملة طوارئ.",
        "c": "لأن اليد أو الرافعة المشغلة لهاغير مريحة في التشغيل.",
        "d": "فرملة الوقوف (الهاندبريك) لا تعمل على جميع عجلات المركبة وقوتها ضعيفة جداً.",
        "answer": "4"
    },
    {
        "id": 2100,
        "question": "ما هي وظيفة جهاز ال-(أي. بي.أس) (ABS)؟",
        "a": "لاستعماله كفرملة إضافية وقت الخطر.",
        "b": "لتمكين السيطرة على المركبة والمقود أثناء الفرملة.",
        "c": "لمنع اهتراء الإطارات.",
        "d": "لمنع الاستعمال الزائد لفرامل المركبة.",
        "answer": "2"
    },
    {
        "id": 2101,
        "question": "لماذا تكون أهمية في سلامة مصدات (طمبونات) المركبة؟",
        "a": "من اجل المحافظة على شكل لائق للمركبة.",
        "b": "من اجل منع الضرر في الحوادث الصعبة.",
        "c": "من اجل تقليل مدى الضرر للمركبة ولركابها عند وقوع حادث.",
        "d": "من اجل الامتناع عن حادث بسيط نسبياً.",
        "answer": "3"
    }
]